README.txt
setup.py
collective/__init__.py
collective.piwik.mediaelement.egg-info/PKG-INFO
collective.piwik.mediaelement.egg-info/SOURCES.txt
collective.piwik.mediaelement.egg-info/dependency_links.txt
collective.piwik.mediaelement.egg-info/entry_points.txt
collective.piwik.mediaelement.egg-info/namespace_packages.txt
collective.piwik.mediaelement.egg-info/not-zip-safe
collective.piwik.mediaelement.egg-info/requires.txt
collective.piwik.mediaelement.egg-info/top_level.txt
collective/piwik/__init__.py
collective/piwik/mediaelement/__init__.py
collective/piwik/mediaelement/configure.zcml
collective/piwik/mediaelement/mediaelement.pt
collective/piwik/mediaelement/tests.py
collective/piwik/mediaelement/version.txt
collective/piwik/mediaelement/view.py
collective/piwik/mediaelement/viewlets.py
docs/CONTRIBUTORS.txt
docs/HISTORY.txt
docs/INSTALL.txt
docs/LICENSE.GPL
docs/LICENSE.txt