Metadata-Version: 1.0
Name: collective.piwik.mediaelement
Version: 0.1
Summary: Analytics support for media elements in Plone using Piwik & MediaElement.js
Home-page: https://github.com/plumi/collective.piwik.mediaelement
Author: unweb.me
Author-email: we@unweb.me
License: GPL
Keywords: video analytics flowplayer piwik plone
Platform: UNKNOWN
Classifier: Framework :: Plone
Classifier: Programming Language :: Python
